SeleniumMouseExtensions/MouseExtensions.py
SeleniumMouseExtensions/__init__.py
robotframework_selenium_mouseextensions-0.1.dist-info/LICENSE
robotframework_selenium_mouseextensions-0.1.dist-info/METADATA
robotframework_selenium_mouseextensions-0.1.dist-info/WHEEL
robotframework_selenium_mouseextensions-0.1.dist-info/top_level.txt
robotframework_selenium_mouseextensions-0.1.dist-info/RECORD
