Metadata-Version: 2.1
Name: robotframework-selenium-mouseextensions
Version: 0.1
Summary: Extra mouse actions missing from the standard SeleniumLibrary
Home-page: https://github.com/mauricekoster/robotframework-selenium-mouseextensions/
Author: Maurice Koster
Author-email: maurice@mauricekoster.com
License: UNKNOWN
Keywords: robotframework selenium
Platform: UNKNOWN
Classifier: Programming Language :: Python :: 3
Classifier: License :: OSI Approved :: MIT License
Classifier: Operating System :: OS Independent
Requires-Python: >=3.7
Requires-Dist: robotframework-seleniumlibrary
